pdfshot/__init__.py
pdfshot/__main__.py
pdfshot/console.py
pdfshot/constants.py
pdfshot-0.2.1.dist-info/entry_points.txt
pdfshot-0.2.1.dist-info/LICENSE
pdfshot-0.2.1.dist-info/WHEEL
pdfshot-0.2.1.dist-info/METADATA
pdfshot-0.2.1.dist-info/RECORD
