Metadata-Version: 2.1
Name: pdfshot
Version: 0.2.1
Summary: A Python CLI to export pages from PDF files as images.
Home-page: https://github.com/joaopalmeiro/pdfshot
License: MIT
Keywords: pdfshot,pdf,screenshot,image,cli
Author: João Palmeiro
Author-email: joaommpalmeiro@gmail.com
Requires-Python: >=3.6,<4.0
Classifier: Development Status :: 3 - Alpha
Classifier: Environment :: Console
Classifier: Intended Audience :: Developers
Classifier: Intended Audience :: Information Technology
Classifier: Intended Audience :: Science/Research
Classifier: License :: OSI Approved :: MIT License
Classifier: Natural Language :: English
Classifier: Operating System :: OS Independent
Classifier: Programming Language :: Python :: 3
Classifier: Programming Language :: Python :: 3.6
Classifier: Programming Language :: Python :: 3.7
Classifier: Programming Language :: Python :: 3.8
Classifier: Programming Language :: Python :: 3.9
Classifier: Programming Language :: Python :: Implementation :: CPython
Classifier: Topic :: Terminals
Classifier: Topic :: Utilities
Requires-Dist: importlib-metadata (>=1.0,<2.0); python_version < "3.8"
Requires-Dist: pdf2image (>=1.14.0,<2.0.0)
Requires-Dist: typer[all] (>=0.3.2,<0.4.0)
Requires-Dist: yaspin (>=1.4.1,<2.0.0)
Project-URL: Bug Tracker, https://github.com/joaopalmeiro/pdfshot/issues
Project-URL: Repository, https://github.com/joaopalmeiro/pdfshot
Project-URL: Twitter, https://twitter.com/joaompalmeiro
